{
  "name": "Ski Alpin 2006",
  "icon": "https://www.mobygames.com/images/covers/s/124475-ski-alpin-2006-windows-front-cover.jpg",
  "attributes": [
    "Published by",
    [
      {
        "link": "https://www.mobygames.com/company/rtl-playtainment",
        "text": "RTL Playtainment"
      }
    ],
    "Developed by",
    [
      {
        "link": "https://www.mobygames.com/company/49games-gmbh",
        "text": "49Games GmbH"
      }
    ],
    "Released",
    [
      {
        "link": "https://www.mobygames.com/game/ski-alpin-2006/release-info",
        "text": "2005"
      }
    ],
    "Platforms",
    [
      {
        "link": "https://www.mobygames.com/game/ps2/ski-alpin-2006",
        "text": "PlayStation 2"
      },
      {
        "link": "https://www.mobygames.com/game/windows/ski-alpin-2006",
        "text": "Windows"
      }
    ],
    "Genre",
    [
      {
        "link": "https://www.mobygames.com/genre/sheet/sports/",
        "text": "Sports"
      }
    ],
    "Perspective",
    [
      {
        "link": "https://www.mobygames.com/genre/sheet/1st-person/",
        "text": "1st-person"
      },
      {
        "link": "https://www.mobygames.com/genre/sheet/3rd-person/",
        "text": "3rd-person (Other)"
      }
    ],
    "Sport",
    [
      {
        "link": "https://www.mobygames.com/genre/sheet/snowboarding-skiing/",
        "text": "Snowboarding / Skiing"
      }
    ],
    "Misc",
    [
      {
        "link": "https://www.mobygames.com/genre/sheet/licensed-title/",
        "text": "Licensed"
      }
    ]
  ],
  "description": "\nRTL Ski Alpin 2006 is a winter sports game with some RPG elements. It is possible to start a career as a skiing star or as a manager. One of the highlights of the game is that you can also play US ski superstar Bode Miller.\n\nThe most important part of the game is the extensive career mode. The player has to to start with an inexperienced but talented skiing amateur. After playing through a number of junior cups it is the aim to develop in a racer able to compete in World cup races. Through some RPG elements it is possible to improve a number of abilities. These improvements can be felt on the track. It is also vital to do the negotiations with sponsors and you can also do some betting against other racers.\n\nThe game features 32 tracks on 18 locations, different difficulty levels and over 900 voiced lines of commentary.\n",
  "screenshots": [],
  "url": "https://www.mobygames.com/game/ski-alpin-2006",
  "altTitles": [
    "\"Ski Alpin 2006 mit Bode Miller\" -- Tag-lined title"
  ]
}